telebot_dialogue
