Metadata-Version: 2.1
Name: telebot_dialogue
Version: 0.3.1
Summary: Library for managing Telegram dialogues using pyTelegramBotAPI.
Home-page: https://github.com/Tiver211/telebot-dialogue
Author: tiver211
Author-email: tiver@tiver211.ru
Classifier: Programming Language :: Python :: 3
Classifier: License :: OSI Approved :: MIT License
Classifier: Operating System :: OS Independent
Requires-Python: >=3.7
License-File: LICENSE
